odoo9_addon_base_phone_popup-9.0.1.0.0-py2.7-nspkg.pth
odoo9_addon_base_phone_popup-9.0.1.0.0.dist-info/top_level.txt
odoo9_addon_base_phone_popup-9.0.1.0.0.dist-info/WHEEL
odoo9_addon_base_phone_popup-9.0.1.0.0.dist-info/RECORD
odoo9_addon_base_phone_popup-9.0.1.0.0.dist-info/metadata.json
odoo9_addon_base_phone_popup-9.0.1.0.0.dist-info/DESCRIPTION.rst
odoo9_addon_base_phone_popup-9.0.1.0.0.dist-info/METADATA
odoo9_addon_base_phone_popup-9.0.1.0.0.dist-info/namespace_packages.txt
odoo_addons/base_phone_popup/__openerp__.py
odoo_addons/base_phone_popup/popup.py
odoo_addons/base_phone_popup/__init__.py
odoo_addons/base_phone_popup/res_users_view.xml
odoo_addons/base_phone_popup/i18n/sl.po
odoo_addons/base_phone_popup/i18n/base_phone_popup.pot
odoo_addons/base_phone_popup/i18n/fr.po
