Metadata-Version: 2.0
Name: odoo9-addon-base-phone-popup
Version: 9.0.1.0.0
Summary: Pop-up the related form view to the user on incoming calls
Home-page: http://www.akretion.com/
Author: UNKNOWN
Author-email: UNKNOWN
License: AGPL-3
Platform: UNKNOWN
Requires-Dist: odoo (<9.1a,>=9.0a)
Requires-Dist: odoo9-addon-base-phone
Requires-Dist: odoo9-addon-web-action-request
Classifier: Programming Language :: Python :: 2.7
Classifier: Framework :: Odoo
Classifier: License :: OSI Approved :: GNU Affero General Public License v3
